ml_callbacks/__init__.py
ml_callbacks/api_client.py
ml_callbacks/callback.py
ml_callbacks/enviroment_callback.py
ml_callbacks/pytorch_enviroment.py
ml_callbacks/pytorch_training.py
ml_callbacks/session_info.py
ml_callbacks/tensorflow_callback.py
ml_callbacks-0.19.8.dist-info/METADATA
ml_callbacks-0.19.8.dist-info/WHEEL
ml_callbacks-0.19.8.dist-info/top_level.txt
ml_callbacks-0.19.8.dist-info/RECORD
