Metadata-Version: 2.1
Name: ml-callbacks
Version: 0.19.8
Summary: Simple ml callbacks to track model performance and state
Home-page: https://github.com/EimantasN/Equusight_BackEnd
Author: Eimantas Noreika
Author-email: noreika.eimantas@gmail.com
License: UNKNOWN
Keywords: ML,PyTorch,Tensorflow,AI
Platform: UNKNOWN
Requires-Python: >=3.6
Requires-Dist: ml-tracking-api (>=1.2.7)
Requires-Dist: nbconvert
Requires-Dist: numpy
Requires-Dist: tqdm
